larisinpy/__init__.py
larisinpy/date.py
larisinpy/encryption.py
larisinpy/connection/__init__.py
larisinpy/connection/firebase.py
larisinpy/exception/__init__.py
larisinpy/exception/json.py
larisinpy-0.1.10.dist-info/METADATA
larisinpy-0.1.10.dist-info/WHEEL
larisinpy-0.1.10.dist-info/top_level.txt
larisinpy-0.1.10.dist-info/RECORD
