Metadata-Version: 2.1
Name: larisinpy
Version: 0.1.10
Summary: Larisinpy
Home-page: https://github.com/mragungsetiaji/larisinpy
Author: Agung Setiaji
Author-email: mragungsetiaji@gmail.com
License: BSD 3-Clause License
Platform: UNKNOWN
Classifier: License :: OSI Approved :: BSD License
Classifier: Programming Language :: Python :: 3.6
Requires-Dist: firebase-admin
Requires-Dist: datetime
Requires-Dist: pytz
Requires-Dist: python-dateutil
